{
    "meta": {
      "title": "Список проверок перед отъездом на длительное время",
      "description": "Обязательный список проверок перед отъездом из дома на длительное время",
      "categoryId": "safety",
      "tags": ["отпуск", "безопасность", "чек-лист", "поездка"],
      "version": "1.0.0",
      "lastUpdated": "2026-04-17",
      "sources": [],
      "itemsFields": {
        "category": "Категория проверки",
        "action": "Что проверяем",
        "status": "Что сделать",
        "notes": "Дополнительные рекомендации"
      }
    },
    "items": [
      {
        "category": "электричество",
        "action": "электроприборы",
        "status": "выключить всё, кроме холодильника",
        "notes": "Отключить удлинители, зарядные устройства, телевизор, компьютер, утюг, чайник. Особенно опасны обогреватели."
      },
      {
        "category": "электричество",
        "action": "свет",
        "status": "проверить и выключить везде",
        "notes": "Во всех комнатах, коридоре, ванной, кладовке. Экономия и пожарная безопасность."
      },
      {
        "category": "электричество",
        "action": "электрощиток",
        "status": "отключить второстепенные линии",
        "notes": "Если есть возможность — отключить автоматы на розеточные группы, кроме холодильника."
      },
      {
        "category": "вода",
        "action": "краны",
        "status": "перекрыть все внутри квартиры",
        "notes": "На кухне, в ванной, туалете. Проверить, не капают ли."
      },
      {
        "category": "вода",
        "action": "стояк",
        "status": "перекрыть квартирный кран на стояке",
        "notes": "Если есть возможность — перекрыть кран на вводе воды в квартиру (перед счётчиком)."
      },
      {
        "category": "вода",
        "action": "бойлер и стиральная машина",
        "status": "отключить от воды и электричества",
        "notes": "Стиралку отключить полностью. Бойлер перевести в режим 'отпуск' или отключить."
      },
      {
        "category": "газ",
        "action": "плита и колонка",
        "status": "перекрыть краны на плите и на вводе",
        "notes": "Проверить все конфорки — они должны быть выключены. Перекрыть газовый кран перед плитой/колонкой."
      },
      {
        "category": "газ",
        "action": "газовый счётчик",
        "status": "убедиться, что нет утечки",
        "notes": "Если есть газ-анализатор — проверить. При запахе газа звонить 104 или 112."
      },
      {
        "category": "окна",
        "action": "окна и форточки",
        "status": "закрыть и проверить замки",
        "notes": "Не оставлять в режиме микропроветривания — это может привлечь воров и опасно при ветре."
      },
      {
        "category": "окна",
        "action": "балкон и лоджия",
        "status": "закрыть и запереть",
        "notes": "Убрать вещи, которые могут упасть или улететь. Проверить дверь балкона."
      },
      {
        "category": "двери",
        "action": "входная дверь",
        "status": "закрыть на все замки",
        "notes": "Проверить, что дверь захлопнута и заперта. Если есть цепочка или задвижка — использовать."
      },
      {
        "category": "двери",
        "action": "внутренние двери",
        "status": "оставить приоткрытыми",
        "notes": "Для циркуляции воздуха и предотвращения плесени (кроме кладовок с химией)."
      },
      {
        "category": "мусор и еда",
        "action": "мусор",
        "status": "вынести все вёдра",
        "notes": "Весь мусор из квартиры. Иначе запах, мухи, тараканы."
      },
      {
        "category": "мусор и еда",
        "action": "холодильник",
        "status": "удалить скоропортящиеся продукты",
        "notes": "Молоко, мясо, рыба, готовые блюда — выбросить или заморозить. Овощи и фрукты тоже могут испортиться."
      },
      {
        "category": "мусор и еда",
        "action": "холодильник (долгая поездка)",
        "status": "разморозить и вымыть",
        "notes": "Если уезжаете на месяц и дольше — разморозить, вымыть, вытереть насухо, оставить дверцу приоткрытой."
      },
      {
        "category": "домашние животные",
        "action": "питомцы",
        "status": "отдать под присмотр или в отель",
        "notes": "Нельзя оставлять одних надолго. Позаботиться о корме, воде, выгуле, лекарствах."
      },
      {
        "category": "домашние животные",
        "action": "аквариум",
        "status": "проверить оборудование",
        "notes": "Настроить автокормушку, фильтры, аэрацию. Попросить кого-то присмотреть."
      },
      {
        "category": "растения",
        "action": "цветы",
        "status": "полить и организовать автополив",
        "notes": "Переставить с подоконника вглубь комнаты. Использовать автополив или попросить соседей."
      },
      {
        "category": "соседи и ключи",
        "action": "ключи",
        "status": "оставить доверенным лицам",
        "notes": "Ключи от квартиры отдать родственникам или соседям, которым доверяете (на случай аварии)."
      },
      {
        "category": "соседи и ключи",
        "action": "почтовый ящик",
        "status": "попросить забирать почту",
        "notes": "Переполненный ящик — признак отсутствия хозяев. Попросить соседей забирать газеты и рекламу."
      },
      {
        "category": "соседи и ключи",
        "action": "предупреждение",
        "status": "сообщить соседям об отъезде",
        "notes": "Оставить свой номер телефона на случай ЧП (залив, пожар)."
      },
      {
        "category": "пожарная безопасность",
        "action": "огнетушитель",
        "status": "проверить срок годности и доступность",
        "notes": "Должен стоять на видном месте, не в кладовке."
      },
      {
        "category": "пожарная безопасность",
        "action": "дымовой извещатель",
        "status": "проверить батарейку",
        "notes": "Если есть АДИ (автономный дымовой извещатель) — убедиться, что работает."
      },
      {
        "category": "документы и ценности",
        "action": "документы и деньги",
        "status": "не оставлять на виду",
        "notes": "Убрать в сейф или надёжное место. Копии документов — отдельно."
      },
      {
        "category": "документы и ценности",
        "action": "ювелирные украшения",
        "status": "убрать в сейф или банк",
        "notes": "Не оставлять в шкатулках на виду."
      },
      {
        "category": "сигнализация",
        "action": "охранная система",
        "status": "активировать перед уходом",
        "notes": "Поставить на охрану. Проверить, что все датчики закрыты (окна, двери)."
      },
      {
        "category": "сигнализация",
        "action": "умный дом",
        "status": "настроить сценарии",
        "notes": "Настроить имитацию присутствия: включение света, радио, штор по расписанию."
      },
      {
        "category": "автомобиль (если едете на машине)",
        "action": "техосмотр",
        "status": "проверить шины, тормоза, жидкости",
        "notes": "Особенно важно перед дальней дорогой. Рекомендация ГИБДД."
      },
      {
        "category": "автомобиль (если едете на машине)",
        "action": "аптечка и огнетушитель",
        "status": "проверить наличие и сроки",
        "notes": "Огнетушитель в машине обязателен по ПДД. Аптечка — должна быть укомплектована."
      },
      {
        "category": "здоровье",
        "action": "лекарства",
        "status": "взять с собой в дорогу",
        "notes": "Не оставлять в машине на жаре. В аптечке: от боли, температуры, аллергии, желудка, пластыри."
      },
      {
        "category": "экстренные номера",
        "action": "телефон",
        "status": "запомнить или сохранить номер 112",
        "notes": "112 — единый номер службы спасения в России. Работает без сети и без сим-карты."
      }
    ]
  }