{
    "meta": {
      "title": "Правила чтения больших чисел",
      "description": "Справочник по чтению многозначных чисел: разбиение на классы, названия разрядов",
      "tags": ["числа", "математика", "разряды"],
      "version": "1.0.0",
      "lastUpdated": "2026-04-17",
      "sources": [],
      "itemsFields": {
        "number": "Пример числа",
        "howToRead": "Как правильно читать",
        "classBreakdown": "Разбивка по классам"
      }
    },
    "items": [
      {
        "number": "1 200 300",
        "howToRead": "один миллион двести тысяч триста",
        "classBreakdown": "1 (миллионы) + 200 (тысячи) + 300 (единицы)"
      },
      {
        "number": "3 005 008",
        "howToRead": "три миллиона пять тысяч восемь",
        "classBreakdown": "3 (миллионы) + 005 (тысячи) + 008 (единицы) → нули опускаются"
      },
      {
        "number": "40 000 000",
        "howToRead": "сорок миллионов",
        "classBreakdown": "40 (миллионы) + 000 (тысячи) + 000 (единицы)"
      },
      {
        "number": "1 000 000 000",
        "howToRead": "один миллиард (один биллион — устаревший вариант)",
        "classBreakdown": "1 (миллиарды/биллионы) + 000 (миллионы) + 000 (тысячи) + 000 (единицы)"
      },
      {
        "number": "1 000 000 000 000",
        "howToRead": "один триллион",
        "classBreakdown": "1 (триллионы) + 000 (миллиарды) + 000 (миллионы) + 000 (тысячи) + 000 (единицы)"
      },
      {
        "number": "2 100 003",
        "howToRead": "два миллиона сто тысяч три",
        "classBreakdown": "2 (миллионы) + 100 (тысячи) + 003 (единицы)"
      },
      {
        "number": "305 020 001",
        "howToRead": "триста пять миллионов двадцать тысяч один",
        "classBreakdown": "305 (миллионы) + 020 (тысячи) + 001 (единицы)"
      }
    ]
  }